newspaper/__init__.py
newspaper/api.py
newspaper/article.py
newspaper/cleaners.py
newspaper/configuration.py
newspaper/extractors.py
newspaper/images.py
newspaper/microservice.py
newspaper/mthreading.py
newspaper/network.py
newspaper/nlp.py
newspaper/outputformatters.py
newspaper/parsers.py
newspaper/settings.py
newspaper/source.py
newspaper/text.py
newspaper/urls.py
newspaper/utils.py
newspaper/version.py
newspaper/resources/misc/google_sources.txt
newspaper/resources/misc/popular_sources.txt
newspaper/resources/misc/stopwords-nlp-en.txt
newspaper/resources/misc/useragents.txt
newspaper/resources/text/stopwords-ar.txt
newspaper/resources/text/stopwords-be.txt
newspaper/resources/text/stopwords-bg.txt
newspaper/resources/text/stopwords-da.txt
newspaper/resources/text/stopwords-de.txt
newspaper/resources/text/stopwords-el.txt
newspaper/resources/text/stopwords-en.txt
newspaper/resources/text/stopwords-es.txt
newspaper/resources/text/stopwords-et.txt
newspaper/resources/text/stopwords-fa.txt
newspaper/resources/text/stopwords-fi.txt
newspaper/resources/text/stopwords-fr.txt
newspaper/resources/text/stopwords-he.txt
newspaper/resources/text/stopwords-hi.txt
newspaper/resources/text/stopwords-hr.txt
newspaper/resources/text/stopwords-hu.txt
newspaper/resources/text/stopwords-id.txt
newspaper/resources/text/stopwords-it.txt
newspaper/resources/text/stopwords-ja.txt
newspaper/resources/text/stopwords-ko.txt
newspaper/resources/text/stopwords-lt.txt
newspaper/resources/text/stopwords-mk.txt
newspaper/resources/text/stopwords-nb.txt
newspaper/resources/text/stopwords-nl.txt
newspaper/resources/text/stopwords-no.txt
newspaper/resources/text/stopwords-pl.txt
newspaper/resources/text/stopwords-pt.txt
newspaper/resources/text/stopwords-ro.txt
newspaper/resources/text/stopwords-ru.txt
newspaper/resources/text/stopwords-sl.txt
newspaper/resources/text/stopwords-sr.txt
newspaper/resources/text/stopwords-sv.txt
newspaper/resources/text/stopwords-sw.txt
enlivensystems_newspaper-0.3.11.dist-info/LICENSE
enlivensystems_newspaper-0.3.11.dist-info/METADATA
enlivensystems_newspaper-0.3.11.dist-info/WHEEL
enlivensystems_newspaper-0.3.11.dist-info/top_level.txt
enlivensystems_newspaper-0.3.11.dist-info/RECORD
