Metadata-Version: 2.1
Name: enlivensystems-newspaper
Version: 0.3.11
Summary: Simplified python article discovery & extraction.
Home-page: https://github.com/codelucas/newspaper/
Author: Lucas Ou-Yang
Author-email: lucasyangpersonal@gmail.com
License: MIT
Platform: UNKNOWN
Classifier: Programming Language :: Python :: 3
Classifier: Natural Language :: English
Classifier: Intended Audience :: Developers
Requires-Dist: beautifulsoup4 (>=4.4.1)
Requires-Dist: cssselect (>=0.9.2)
Requires-Dist: feedfinder2 (>=0.0.4)
Requires-Dist: feedparser (>=5.2.1)
Requires-Dist: jieba3k (>=0.35.1)
Requires-Dist: lxml (>=3.6.0)
Requires-Dist: nltk (>=3.2.1)
Requires-Dist: Pillow (>=3.3.0)
Requires-Dist: pythainlp (>=1.7.2)
Requires-Dist: python-dateutil (>=2.5.3)
Requires-Dist: PyYAML (>=3.11)
Requires-Dist: requests (>=2.10.0)
Requires-Dist: tinysegmenter (==0.3)
Requires-Dist: tldextract (>=2.0.1)
Requires-Dist: yake (>=git+https://github.com/LIAAD/yake.git)
Requires-Dist: pandas (>=0.25.3)
Requires-Dist: fastapi
Requires-Dist: uvicorn
